screenshotz/__init__.py
screenshotz/__main__.py
screenshotz/code.py
screenshotz/command.py
screenshotz-3.11.dist-info/entry_points.txt
screenshotz-3.11.dist-info/WHEEL
screenshotz-3.11.dist-info/METADATA
screenshotz-3.11.dist-info/RECORD
